{"qid":"Q1259684","name":"Ivan Picelj","birthYear":1924,"deathYear":2011,"alive":false,"gender":"male","movement":"No movement listed","citizenship":"Croatia","citizenships":["Croatia"],"birthDecade":1920,"inDegree":0,"outDegree":0,"totalDegree":0,"birthPlace":"Okučani","birthCountry":"Croatia","deathPlace":"Zagreb","deathCountry":"Croatia","nativeName":null,"nativeLang":null,"image":null,"authorityTypes":["bnf","dnb","lcnaf","ulan","viaf"],"authorityLinks":[{"id":"14968605t","type":"bnf","url":"https://catalogue.bnf.fr/ark:/12148/cb14968605t"},{"id":"120731495","type":"dnb","url":"https://d-nb.info/gnd/120731495"},{"id":"n85093822","type":"lcnaf","url":"https://id.loc.gov/authorities/names/n85093822"},{"id":"500013861","type":"ulan","url":"https://www.getty.edu/vow/ULANFullDisplay?find=&role=&nation=&subjectid=500013861"},{"id":"62386402","type":"viaf","url":"https://viaf.org/en/viaf/62386402"}],"sitelinkCount":7,"nonEnSitelinkCount":6,"inclusionSignals":["sitelinks"],"gettyVerified":{"ulanId":"500013861","url":"https://www.getty.edu/vow/ULANFullDisplay?find=&role=&nation=&subjectid=500013861","label":"Picelj, Ivan","birthYear":1924,"birthPlace":"Okučani","deathYear":2024,"deathPlace":null,"nationalities":["Yugoslav"],"agreement":{"birthYear":"match","deathYear":"off_big","birthPlace":true,"deathPlace":null,"natJaccard":0}}}