{"qid":"Q1298862","name":"Egon Rheinberger","birthYear":1870,"deathYear":1936,"alive":false,"gender":"male","movement":"No movement listed","citizenship":"Liechtenstein","citizenships":["Liechtenstein"],"birthDecade":1870,"inDegree":0,"outDegree":0,"totalDegree":0,"birthPlace":"Vaduz","birthCountry":"Liechtenstein","deathPlace":"Gutenberg Castle","deathCountry":"Liechtenstein","nativeName":null,"nativeLang":null,"image":null,"authorityTypes":["dnb","ulan","viaf"],"authorityLinks":[{"id":"139122931","type":"dnb","url":"https://d-nb.info/gnd/139122931"},{"id":"500232893","type":"ulan","url":"https://www.getty.edu/vow/ULANFullDisplay?find=&role=&nation=&subjectid=500232893"},{"id":"100428908","type":"viaf","url":"https://viaf.org/en/viaf/100428908"}],"sitelinkCount":3,"nonEnSitelinkCount":3,"inclusionSignals":["sitelinks"]}