{"qid":"Q1378156","name":"Manuel Pereira da Silva","birthYear":1920,"deathYear":2003,"alive":false,"gender":"male","movement":"No movement listed","citizenship":"Portugal","citizenships":["Portugal"],"birthDecade":1920,"inDegree":0,"outDegree":0,"totalDegree":0,"birthPlace":"Vila Nova de Gaia","birthCountry":"Portugal","deathPlace":null,"deathCountry":null,"nativeName":"Manuel Pereira da Silva","nativeLang":"pt","image":"http://commons.wikimedia.org/wiki/Special:FilePath/Auto-retrato.jpg","authorityTypes":[],"authorityLinks":[],"sitelinkCount":7,"nonEnSitelinkCount":6,"inclusionSignals":["sitelinks"]}