{"qid":"Q1433059","name":"Jiří Kaloč","birthYear":1943,"deathYear":2025,"alive":false,"gender":"male","movement":"No movement listed","citizenship":"Czechoslovakia","citizenships":["Czechoslovakia"],"birthDecade":1940,"inDegree":0,"outDegree":0,"totalDegree":0,"birthPlace":"Sezimovo Ústí","birthCountry":"Czech Republic","deathPlace":null,"deathCountry":null,"nativeName":null,"nativeLang":null,"image":"http://commons.wikimedia.org/wiki/Special:FilePath/Ji%C5%99%C3%AD%20Kalo%C4%8D%20%282019%29.jpg","authorityTypes":["dnb","lcnaf","viaf"],"authorityLinks":[{"id":"1013122356","type":"dnb","url":"https://d-nb.info/gnd/1013122356"},{"id":"no2002078340","type":"lcnaf","url":"https://id.loc.gov/authorities/names/no2002078340"},{"id":"9517591","type":"viaf","url":"https://viaf.org/en/viaf/9517591"}],"sitelinkCount":3,"nonEnSitelinkCount":3,"inclusionSignals":["sitelinks"]}