{"qid":"Q152788","name":"Emil Nolde","birthYear":1867,"deathYear":1956,"alive":false,"gender":"male","movement":"Expressionism","citizenship":"Germany","citizenships":["Germany","Kingdom of Denmark"],"birthDecade":1860,"inDegree":3,"outDegree":0,"totalDegree":3,"birthPlace":"Nolde","birthCountry":"Denmark","deathPlace":"Seeb\u00fcll","deathCountry":"Germany","nativeName":"Emil Nolde","nativeLang":"de","image":"http://commons.wikimedia.org/wiki/Special:FilePath/WP%20Emil%20Nolde.jpg","authorityTypes":["bne","bnf","dnb","lcnaf","ndl","ulan","viaf"],"authorityLinks":[{"id":"XX1049432","type":"bne","url":"https://datos.bne.es/persona/XX1049432"},{"id":"12704529q","type":"bnf","url":"https://catalogue.bnf.fr/ark:/12148/cb12704529q"},{"id":"118588494","type":"dnb","url":"https://d-nb.info/gnd/118588494"},{"id":"n79135037","type":"lcnaf","url":"https://id.loc.gov/authorities/names/n79135037"},{"id":"00451414","type":"ndl","url":"https://id.ndl.go.jp/auth/ndlna/00451414"},{"id":"500003109","type":"ulan","url":"https://www.getty.edu/vow/ULANFullDisplay?find=&role=&nation=&subjectid=500003109"},{"id":"37040576","type":"viaf","url":"https://viaf.org/en/viaf/37040576"}],"sitelinkCount":51,"nonEnSitelinkCount":50,"inclusionSignals":["movement","edge","multi_citz","sitelinks"]}