{"qid":"Q153104","name":"Otto Dix","birthYear":1891,"deathYear":1969,"alive":false,"gender":"male","movement":"Expressionism","citizenship":"Germany","citizenships":["Germany"],"birthDecade":1890,"inDegree":4,"outDegree":0,"totalDegree":4,"birthPlace":"Untermhaus","birthCountry":"Germany","deathPlace":"Singen","deathCountry":"Germany","nativeName":"Otto Dix","nativeLang":"de","image":"http://commons.wikimedia.org/wiki/Special:FilePath/Otto%20Dix%20by%20Hugo%20Erfurth%2C%20c.%201929.jpg","authorityTypes":["bne","bnf","dnb","lcnaf","ndl","ulan","viaf"],"authorityLinks":[{"id":"XX1297279","type":"bne","url":"https://datos.bne.es/persona/XX1297279"},{"id":"119419770","type":"bnf","url":"https://catalogue.bnf.fr/ark:/12148/cb119419770"},{"id":"118526103","type":"dnb","url":"https://d-nb.info/gnd/118526103"},{"id":"n50028833","type":"lcnaf","url":"https://id.loc.gov/authorities/names/n50028833"},{"id":"00465642","type":"ndl","url":"https://id.ndl.go.jp/auth/ndlna/00465642"},{"id":"500028047","type":"ulan","url":"https://www.getty.edu/vow/ULANFullDisplay?find=&role=&nation=&subjectid=500028047"},{"id":"46769170","type":"viaf","url":"https://viaf.org/en/viaf/46769170"}],"sitelinkCount":62,"nonEnSitelinkCount":61,"inclusionSignals":["movement","edge","sitelinks"],"gettyVerified":{"ulanId":"500028047","url":"https://www.getty.edu/vow/ULANFullDisplay?find=&role=&nation=&subjectid=500028047","label":"Dix, Otto","birthYear":1891,"birthPlace":"Untermhaus","deathYear":1969,"deathPlace":"Singen","nationalities":["German"],"agreement":{"birthYear":"match","deathYear":"match","birthPlace":true,"deathPlace":true,"natJaccard":1}}}