{"qid":"Q1887115","name":"Achiam","birthYear":1916,"deathYear":2005,"alive":false,"gender":"male","movement":"abstract art","citizenship":"France","citizenships":["France","Israel"],"birthDecade":1910,"inDegree":0,"outDegree":0,"totalDegree":0,"birthPlace":"Palestine","birthCountry":"Israel","deathPlace":"15th arrondissement of Paris","deathCountry":"France","nativeName":"Achiam","nativeLang":"fr","image":"http://commons.wikimedia.org/wiki/Special:FilePath/Achiam%20sculptant%20Torse%20de%20danseuse%20-.JPG","authorityTypes":["bnf","dnb","lcnaf","ulan","viaf"],"authorityLinks":[{"id":"17846570b","type":"bnf","url":"https://catalogue.bnf.fr/ark:/12148/cb17846570b"},{"id":"110682696","type":"dnb","url":"https://d-nb.info/gnd/110682696"},{"id":"nr96018740","type":"lcnaf","url":"https://id.loc.gov/authorities/names/nr96018740"},{"id":"500191992","type":"ulan","url":"https://www.getty.edu/vow/ULANFullDisplay?find=&role=&nation=&subjectid=500191992"},{"id":"56508417","type":"viaf","url":"https://viaf.org/en/viaf/56508417"}],"sitelinkCount":7,"nonEnSitelinkCount":6,"inclusionSignals":["movement","multi_citz","sitelinks"],"gettyVerified":{"ulanId":"500191992","url":"https://www.getty.edu/vow/ULANFullDisplay?find=&role=&nation=&subjectid=500191992","label":"Achiam, Israel Shoshany","birthYear":1916,"birthPlace":null,"deathYear":2005,"deathPlace":null,"nationalities":[],"agreement":{"birthYear":"match","deathYear":"match","birthPlace":null,"deathPlace":null,"natJaccard":0}}}