{"qid":"Q2032941","name":"Emilio Sala","birthYear":1864,"deathYear":1920,"alive":false,"gender":"male","movement":"No movement listed","citizenship":"Kingdom of Italy","citizenships":["Kingdom of Italy"],"birthDecade":1860,"inDegree":0,"outDegree":0,"totalDegree":0,"birthPlace":"Milan","birthCountry":"Italy","deathPlace":"Gorlaprecotto","deathCountry":"Italy","nativeName":null,"nativeLang":null,"image":null,"authorityTypes":[],"authorityLinks":[],"sitelinkCount":10,"nonEnSitelinkCount":9,"inclusionSignals":["sitelinks"]}