{"qid":"Q212346","name":"Christos Kapralos","birthYear":1909,"deathYear":1993,"alive":false,"gender":"male","movement":"No movement listed","citizenship":"Greece","citizenships":["Greece"],"birthDecade":1900,"inDegree":2,"outDegree":0,"totalDegree":2,"birthPlace":"Panaitolio","birthCountry":"Greece","deathPlace":"Athens","deathCountry":"Greece","nativeName":"Χρήστος Καπράλος","nativeLang":"el","image":null,"authorityTypes":["dnb","lcnaf","ulan","viaf"],"authorityLinks":[{"id":"119366452","type":"dnb","url":"https://d-nb.info/gnd/119366452"},{"id":"n84019698","type":"lcnaf","url":"https://id.loc.gov/authorities/names/n84019698"},{"id":"500123657","type":"ulan","url":"https://www.getty.edu/vow/ULANFullDisplay?find=&role=&nation=&subjectid=500123657"},{"id":"50034624","type":"viaf","url":"https://viaf.org/en/viaf/50034624"}],"sitelinkCount":6,"nonEnSitelinkCount":5,"inclusionSignals":["edge","sitelinks"],"gettyVerified":{"ulanId":"500123657","url":"https://www.getty.edu/vow/ULANFullDisplay?find=&role=&nation=&subjectid=500123657","label":"Capralos, Christos","birthYear":1909,"birthPlace":null,"deathYear":1993,"deathPlace":null,"nationalities":[],"agreement":{"birthYear":"match","deathYear":"match","birthPlace":null,"deathPlace":null,"natJaccard":0}}}