{"qid":"Q2272827","name":"Cor Hund","birthYear":1915,"deathYear":2008,"alive":false,"gender":"male","movement":"No movement listed","citizenship":"Kingdom of the Netherlands","citizenships":["Kingdom of the Netherlands"],"birthDecade":1910,"inDegree":2,"outDegree":0,"totalDegree":2,"birthPlace":"Amsterdam","birthCountry":"Netherlands","deathPlace":"Amsterdam","deathCountry":"Netherlands","nativeName":"Cornelis Hund","nativeLang":"nl","image":"http://commons.wikimedia.org/wiki/Special:FilePath/Gerrit%20Jan%20van%20der%20Veen%20%281965%29.jpg","authorityTypes":["bnf","dnb","lcnaf","viaf"],"authorityLinks":[{"id":"15511662c","type":"bnf","url":"https://catalogue.bnf.fr/ark:/12148/cb15511662c"},{"id":"129069035","type":"dnb","url":"https://d-nb.info/gnd/129069035"},{"id":"no2006032973","type":"lcnaf","url":"https://id.loc.gov/authorities/names/no2006032973"},{"id":"44049143","type":"viaf","url":"https://viaf.org/en/viaf/44049143"}],"sitelinkCount":2,"nonEnSitelinkCount":2,"inclusionSignals":["edge"]}