{"qid":"Q2297520","name":"Joop de Blaauw","birthYear":1941,"deathYear":null,"alive":true,"gender":"male","movement":"abstract art","citizenship":"Kingdom of the Netherlands","citizenships":["Kingdom of the Netherlands"],"birthDecade":1940,"inDegree":0,"outDegree":0,"totalDegree":0,"birthPlace":"Amsterdam","birthCountry":"Netherlands","deathPlace":null,"deathCountry":null,"nativeName":null,"nativeLang":null,"image":null,"authorityTypes":[],"authorityLinks":[],"sitelinkCount":1,"nonEnSitelinkCount":1,"inclusionSignals":["movement"]}