{"qid":"Q235281","name":"Helen Frankenthaler","birthYear":1928,"deathYear":2011,"alive":false,"gender":"female","movement":"abstract expressionism","citizenship":"United States","citizenships":["United States"],"birthDecade":1920,"inDegree":3,"outDegree":0,"totalDegree":3,"birthPlace":"Manhattan","birthCountry":"United States","deathPlace":"Darien","deathCountry":"United States","nativeName":"Helen Frankenthaler","nativeLang":"en","image":"http://commons.wikimedia.org/wiki/Special:FilePath/2001%20National%20Medal%20of%20Arts%20Recipient%20Helen%20Frankenthaler%20%28cropped%29.jpg","authorityTypes":["bne","bnf","dnb","lcnaf","ulan","viaf"],"authorityLinks":[{"id":"XX932700","type":"bne","url":"https://datos.bne.es/persona/XX932700"},{"id":"12173339n","type":"bnf","url":"https://catalogue.bnf.fr/ark:/12148/cb12173339n"},{"id":"119163926","type":"dnb","url":"https://d-nb.info/gnd/119163926"},{"id":"n80038383","type":"lcnaf","url":"https://id.loc.gov/authorities/names/n80038383"},{"id":"500115813","type":"ulan","url":"https://www.getty.edu/vow/ULANFullDisplay?find=&role=&nation=&subjectid=500115813"},{"id":"84991528","type":"viaf","url":"https://viaf.org/en/viaf/84991528"}],"sitelinkCount":33,"nonEnSitelinkCount":32,"inclusionSignals":["movement","edge","sitelinks"],"gettyVerified":{"ulanId":"500115813","url":"https://www.getty.edu/vow/ULANFullDisplay?find=&role=&nation=&subjectid=500115813","label":"Frankenthaler, Helen","birthYear":1928,"birthPlace":"New York","deathYear":2011,"deathPlace":"Darien","nationalities":["American"],"agreement":{"birthYear":"match","deathYear":"match","birthPlace":false,"deathPlace":true,"natJaccard":1}}}