{"qid":"Q2389448","name":"Takera Narita","birthYear":1939,"deathYear":2001,"alive":false,"gender":"male","movement":"abstract art","citizenship":"Japan","citizenships":["Japan","Empire of Japan"],"birthDecade":1930,"inDegree":0,"outDegree":0,"totalDegree":0,"birthPlace":"Tokyo","birthCountry":"Japan","deathPlace":null,"deathCountry":null,"nativeName":"成田武羅","nativeLang":"ja","image":"http://commons.wikimedia.org/wiki/Special:FilePath/Symposion%20Lindabrunn%2C%20Takera%20Narita%201968.jpg","authorityTypes":["dnb","ndl","viaf"],"authorityLinks":[{"id":"1042312869","type":"dnb","url":"https://d-nb.info/gnd/1042312869"},{"id":"01145772","type":"ndl","url":"https://id.ndl.go.jp/auth/ndlna/01145772"},{"id":"258570849","type":"viaf","url":"https://viaf.org/en/viaf/258570849"}],"sitelinkCount":2,"nonEnSitelinkCount":2,"inclusionSignals":["movement","multi_citz"]}