{"qid":"Q2824195","name":"Adelaide Johnson","birthYear":1859,"deathYear":1955,"alive":false,"gender":"female","movement":"No movement listed","citizenship":"United States","citizenships":["United States"],"birthDecade":1850,"inDegree":0,"outDegree":0,"totalDegree":0,"birthPlace":"Plymouth","birthCountry":"United States","deathPlace":"Washington, D.C.","deathCountry":"United States","nativeName":"Adelaide Johnson","nativeLang":"en","image":"http://commons.wikimedia.org/wiki/Special:FilePath/Flickr%20-%20USCapitol%20-%20Adelaide%20Johnson%20%281846-1955%29%20-%20Women%20Artists.jpg","authorityTypes":["dnb","lcnaf","ulan","viaf"],"authorityLinks":[{"id":"1117492001","type":"dnb","url":"https://d-nb.info/gnd/1117492001"},{"id":"n97004036","type":"lcnaf","url":"https://id.loc.gov/authorities/names/n97004036"},{"id":"500335895","type":"ulan","url":"https://www.getty.edu/vow/ULANFullDisplay?find=&role=&nation=&subjectid=500335895"},{"id":"21416030","type":"viaf","url":"https://viaf.org/en/viaf/21416030"}],"sitelinkCount":14,"nonEnSitelinkCount":13,"inclusionSignals":["sitelinks"]}