{"qid":"Q2908768","name":"Richard Lippold","birthYear":1915,"deathYear":2002,"alive":false,"gender":"male","movement":"No movement listed","citizenship":"United States","citizenships":["United States"],"birthDecade":1910,"inDegree":0,"outDegree":0,"totalDegree":0,"birthPlace":"Milwaukee","birthCountry":"United States","deathPlace":"St. Francis Hospital","deathCountry":"United States","nativeName":null,"nativeLang":null,"image":null,"authorityTypes":["bnf","dnb","lcnaf","ulan","viaf"],"authorityLinks":[{"id":"16229706x","type":"bnf","url":"https://catalogue.bnf.fr/ark:/12148/cb16229706x"},{"id":"143159658","type":"dnb","url":"https://d-nb.info/gnd/143159658"},{"id":"n91031472","type":"lcnaf","url":"https://id.loc.gov/authorities/names/n91031472"},{"id":"500006078","type":"ulan","url":"https://www.getty.edu/vow/ULANFullDisplay?find=&role=&nation=&subjectid=500006078"},{"id":"95717920","type":"viaf","url":"https://viaf.org/en/viaf/95717920"}],"sitelinkCount":5,"nonEnSitelinkCount":4,"inclusionSignals":["sitelinks"]}