{"qid":"Q322038","name":"Endre Nemes","birthYear":1909,"deathYear":1985,"alive":false,"gender":"male","movement":"No movement listed","citizenship":"Sweden","citizenships":["Sweden"],"birthDecade":1900,"inDegree":0,"outDegree":0,"totalDegree":0,"birthPlace":"P\u00e9csv\u00e1rad","birthCountry":"Hungary","deathPlace":"Stockholm","deathCountry":"Sweden","nativeName":null,"nativeLang":null,"image":"http://commons.wikimedia.org/wiki/Special:FilePath/Endre-Nemes-%28photo-B-L-Nemes%29.jpg","authorityTypes":["bnf","dnb","lcnaf","ulan","viaf"],"authorityLinks":[{"id":"122203241","type":"bnf","url":"https://catalogue.bnf.fr/ark:/12148/cb122203241"},{"id":"119043378","type":"dnb","url":"https://d-nb.info/gnd/119043378"},{"id":"n84222175","type":"lcnaf","url":"https://id.loc.gov/authorities/names/n84222175"},{"id":"500012514","type":"ulan","url":"https://www.getty.edu/vow/ULANFullDisplay?find=&role=&nation=&subjectid=500012514"},{"id":"7441195","type":"viaf","url":"https://viaf.org/en/viaf/7441195"}],"sitelinkCount":9,"nonEnSitelinkCount":8,"inclusionSignals":["sitelinks"]}