{"qid":"Q330465","name":"Abraham Ostrzega","birthYear":1889,"deathYear":1942,"alive":false,"gender":"male","movement":"No movement listed","citizenship":"Second Polish Republic","citizenships":["Second Polish Republic"],"birthDecade":1880,"inDegree":0,"outDegree":0,"totalDegree":0,"birthPlace":"Okuniew","birthCountry":"Poland","deathPlace":"Treblinka extermination camp","deathCountry":"Poland","nativeName":"Abraham Ostrzega","nativeLang":"pl","image":null,"authorityTypes":["dnb","viaf"],"authorityLinks":[{"id":"129480331X","type":"dnb","url":"https://d-nb.info/gnd/129480331X"},{"id":"5224151778223118130000","type":"viaf","url":"https://viaf.org/en/viaf/5224151778223118130000"}],"sitelinkCount":3,"nonEnSitelinkCount":3,"inclusionSignals":["sitelinks"]}