{"qid":"Q34618","name":"Gustave Courbet","birthYear":1819,"deathYear":1877,"alive":false,"gender":"male","movement":"French Realism","citizenship":"France","citizenships":["France"],"birthDecade":1810,"inDegree":9,"outDegree":3,"totalDegree":12,"birthPlace":"Ornans","birthCountry":"France","deathPlace":"La Tour-de-Peilz","deathCountry":"Switzerland","nativeName":"Gustave Courbet","nativeLang":"fr","image":"http://commons.wikimedia.org/wiki/Special:FilePath/Gustave%20Courbet%2C%20photograph%20Atelier%20Nadar%2C%20c.%201860s.jpg","authorityTypes":["bne","bnf","dnb","lcnaf","ndl","ulan","viaf"],"authorityLinks":[{"id":"XX985701","type":"bne","url":"https://datos.bne.es/persona/XX985701"},{"id":"120519068","type":"bnf","url":"https://catalogue.bnf.fr/ark:/12148/cb120519068"},{"id":"118522450","type":"dnb","url":"https://d-nb.info/gnd/118522450"},{"id":"n80057228","type":"lcnaf","url":"https://id.loc.gov/authorities/names/n80057228"},{"id":"00436747","type":"ndl","url":"https://id.ndl.go.jp/auth/ndlna/00436747"},{"id":"500010927","type":"ulan","url":"https://www.getty.edu/vow/ULANFullDisplay?find=&role=&nation=&subjectid=500010927"},{"id":"22160734","type":"viaf","url":"https://viaf.org/en/viaf/22160734"}],"sitelinkCount":72,"nonEnSitelinkCount":71,"inclusionSignals":["movement","edge","sitelinks"]}