{"qid":"Q3474524","name":"Saverio Lucariello","birthYear":1958,"deathYear":2023,"alive":false,"gender":"male","movement":"No movement listed","citizenship":"France","citizenships":["Italy","France"],"birthDecade":1950,"inDegree":0,"outDegree":0,"totalDegree":0,"birthPlace":"Chiaia","birthCountry":"Italy","deathPlace":"Sens","deathCountry":"France","nativeName":null,"nativeLang":null,"image":null,"authorityTypes":["bnf","dnb","lcnaf","ulan","viaf"],"authorityLinks":[{"id":"12115330s","type":"bnf","url":"https://catalogue.bnf.fr/ark:/12148/cb12115330s"},{"id":"123783798","type":"dnb","url":"https://d-nb.info/gnd/123783798"},{"id":"no2001091165","type":"lcnaf","url":"https://id.loc.gov/authorities/names/no2001091165"},{"id":"500194551","type":"ulan","url":"https://www.getty.edu/vow/ULANFullDisplay?find=&role=&nation=&subjectid=500194551"},{"id":"41498641","type":"viaf","url":"https://viaf.org/en/viaf/41498641"}],"sitelinkCount":1,"nonEnSitelinkCount":1,"inclusionSignals":["multi_citz"],"gettyVerified":{"ulanId":"500194551","url":"https://www.getty.edu/vow/ULANFullDisplay?find=&role=&nation=&subjectid=500194551","label":"Lucariello, Saverio","birthYear":1958,"birthPlace":null,"deathYear":2078,"deathPlace":null,"nationalities":["Italian"],"agreement":{"birthYear":"match","deathYear":"off_big","birthPlace":null,"deathPlace":null,"natJaccard":0.5}}}