{"qid":"Q460233","name":"Monica Bonvicini","birthYear":1965,"deathYear":null,"alive":true,"gender":"female","movement":"No movement listed","citizenship":"Italy","citizenships":["Italy"],"birthDecade":1960,"inDegree":0,"outDegree":0,"totalDegree":0,"birthPlace":"Venice","birthCountry":"Italy","deathPlace":null,"deathCountry":null,"nativeName":null,"nativeLang":null,"image":null,"authorityTypes":["bne","bnf","dnb","lcnaf","ulan","viaf"],"authorityLinks":[{"id":"XX5151395","type":"bne","url":"https://datos.bne.es/persona/XX5151395"},{"id":"13623291f","type":"bnf","url":"https://catalogue.bnf.fr/ark:/12148/cb13623291f"},{"id":"122347579","type":"dnb","url":"https://d-nb.info/gnd/122347579"},{"id":"n2001113721","type":"lcnaf","url":"https://id.loc.gov/authorities/names/n2001113721"},{"id":"500336376","type":"ulan","url":"https://www.getty.edu/vow/ULANFullDisplay?find=&role=&nation=&subjectid=500336376"},{"id":"52568464","type":"viaf","url":"https://viaf.org/en/viaf/52568464"}],"sitelinkCount":10,"nonEnSitelinkCount":9,"inclusionSignals":["sitelinks"],"gettyVerified":{"ulanId":"500336376","url":"https://www.getty.edu/vow/ULANFullDisplay?find=&role=&nation=&subjectid=500336376","label":"Bonvicini, Monica","birthYear":1965,"birthPlace":"Venezia","deathYear":2085,"deathPlace":null,"nationalities":["Italian"],"agreement":{"birthYear":"match","deathYear":"missing","birthPlace":false,"deathPlace":null,"natJaccard":1}}}