{"qid":"Q461935","name":"Ernesto Treccani","birthYear":1920,"deathYear":2009,"alive":false,"gender":"male","movement":"No movement listed","citizenship":"Kingdom of Italy","citizenships":["Italy","Kingdom of Italy"],"birthDecade":1920,"inDegree":0,"outDegree":0,"totalDegree":0,"birthPlace":"Milan","birthCountry":"Italy","deathPlace":"Milan","deathCountry":"Italy","nativeName":"Ernesto Treccani","nativeLang":"it","image":null,"authorityTypes":["bnf","dnb","lcnaf","ulan","viaf"],"authorityLinks":[{"id":"12359067f","type":"bnf","url":"https://catalogue.bnf.fr/ark:/12148/cb12359067f"},{"id":"118623729","type":"dnb","url":"https://d-nb.info/gnd/118623729"},{"id":"n50049842","type":"lcnaf","url":"https://id.loc.gov/authorities/names/n50049842"},{"id":"500017863","type":"ulan","url":"https://www.getty.edu/vow/ULANFullDisplay?find=&role=&nation=&subjectid=500017863"},{"id":"74646170","type":"viaf","url":"https://viaf.org/en/viaf/74646170"}],"sitelinkCount":7,"nonEnSitelinkCount":6,"inclusionSignals":["multi_citz","sitelinks"],"gettyVerified":{"ulanId":"500017863","url":"https://www.getty.edu/vow/ULANFullDisplay?find=&role=&nation=&subjectid=500017863","label":"Treccani, Ernesto","birthYear":1920,"birthPlace":"Milano","deathYear":2020,"deathPlace":null,"nationalities":["Italian"],"agreement":{"birthYear":"match","deathYear":"off_big","birthPlace":true,"deathPlace":null,"natJaccard":0.5}}}