{"qid":"Q540789","name":"Erich Ott","birthYear":1944,"deathYear":null,"alive":true,"gender":"male","movement":"No movement listed","citizenship":"Germany","citizenships":["Germany"],"birthDecade":1940,"inDegree":0,"outDegree":0,"totalDegree":0,"birthPlace":"Oberammergau","birthCountry":"Germany","deathPlace":null,"deathCountry":null,"nativeName":null,"nativeLang":null,"image":null,"authorityTypes":["dnb","viaf"],"authorityLinks":[{"id":"1064961622","type":"dnb","url":"https://d-nb.info/gnd/1064961622"},{"id":"314790876","type":"viaf","url":"https://viaf.org/en/viaf/314790876"}],"sitelinkCount":5,"nonEnSitelinkCount":4,"inclusionSignals":["sitelinks"]}