{"qid":"Q556328","name":"Giulio Turcato","birthYear":1912,"deathYear":1995,"alive":false,"gender":"male","movement":"No movement listed","citizenship":"Kingdom of Italy","citizenships":["Italy","Kingdom of Italy"],"birthDecade":1910,"inDegree":0,"outDegree":0,"totalDegree":0,"birthPlace":"Mantua","birthCountry":"Italy","deathPlace":"Rome","deathCountry":"Italy","nativeName":null,"nativeLang":null,"image":null,"authorityTypes":["bnf","dnb","lcnaf","ulan","viaf"],"authorityLinks":[{"id":"12004127q","type":"bnf","url":"https://catalogue.bnf.fr/ark:/12148/cb12004127q"},{"id":"11862461X","type":"dnb","url":"https://d-nb.info/gnd/11862461X"},{"id":"n84158935","type":"lcnaf","url":"https://id.loc.gov/authorities/names/n84158935"},{"id":"500003943","type":"ulan","url":"https://www.getty.edu/vow/ULANFullDisplay?find=&role=&nation=&subjectid=500003943"},{"id":"10638939","type":"viaf","url":"https://viaf.org/en/viaf/10638939"}],"sitelinkCount":7,"nonEnSitelinkCount":6,"inclusionSignals":["multi_citz","sitelinks"],"gettyVerified":{"ulanId":"500003943","url":"https://www.getty.edu/vow/ULANFullDisplay?find=&role=&nation=&subjectid=500003943","label":"Turcato, Giulio","birthYear":1912,"birthPlace":null,"deathYear":1995,"deathPlace":null,"nationalities":["Italian"],"agreement":{"birthYear":"match","deathYear":"match","birthPlace":null,"deathPlace":null,"natJaccard":0.5}}}