{"qid":"Q561184","name":"G\u00fcnther F\u00f6rg","birthYear":1952,"deathYear":2013,"alive":false,"gender":"male","movement":"No movement listed","citizenship":"Germany","citizenships":["Germany"],"birthDecade":1950,"inDegree":0,"outDegree":0,"totalDegree":0,"birthPlace":"F\u00fcssen","birthCountry":"Germany","deathPlace":"Colombier","deathCountry":"Switzerland","nativeName":"G\u00fcnther F\u00f6rg","nativeLang":"de","image":"http://commons.wikimedia.org/wiki/Special:FilePath/From%20left%20to%20right%2C%20Heike-Melba%20Fendel%2C%20Franz%20Dahlem%2C%20Brigitte%20Schenk%2C%20G%C3%BCnther%20F%C3%B6rg%20%28cropped%29.jpg","authorityTypes":["bne","bnf","dnb","lcnaf","ulan","viaf"],"authorityLinks":[{"id":"XX1329484","type":"bne","url":"https://datos.bne.es/persona/XX1329484"},{"id":"121681858","type":"bnf","url":"https://catalogue.bnf.fr/ark:/12148/cb121681858"},{"id":"118692011","type":"dnb","url":"https://d-nb.info/gnd/118692011"},{"id":"n86026887","type":"lcnaf","url":"https://id.loc.gov/authorities/names/n86026887"},{"id":"500047248","type":"ulan","url":"https://www.getty.edu/vow/ULANFullDisplay?find=&role=&nation=&subjectid=500047248"},{"id":"9888285","type":"viaf","url":"https://viaf.org/en/viaf/9888285"}],"sitelinkCount":14,"nonEnSitelinkCount":13,"inclusionSignals":["sitelinks"]}