{"qid":"Q622586","name":"Fuad Abdurahmanov","birthYear":1915,"deathYear":1971,"alive":false,"gender":"male","movement":"No movement listed","citizenship":"Soviet Union","citizenships":["Soviet Union"],"birthDecade":1910,"inDegree":1,"outDegree":0,"totalDegree":1,"birthPlace":"Shaki","birthCountry":"Azerbaijan","deathPlace":"Baku","deathCountry":"Azerbaijan","nativeName":"Fuad H\u0259s\u0259n o\u011flu \u018fbd\u00fcr\u0259hmanov","nativeLang":"az","image":null,"authorityTypes":["lcnaf","viaf"],"authorityLinks":[{"id":"n88018063","type":"lcnaf","url":"https://id.loc.gov/authorities/names/n88018063"},{"id":"8923467","type":"viaf","url":"https://viaf.org/en/viaf/8923467"}],"sitelinkCount":21,"nonEnSitelinkCount":20,"inclusionSignals":["edge","sitelinks"]}