{"qid":"Q706619","name":"Charles Auguste Fraikin","birthYear":1817,"deathYear":1893,"alive":false,"gender":"male","movement":"No movement listed","citizenship":"Belgium","citizenships":["Belgium"],"birthDecade":1810,"inDegree":0,"outDegree":0,"totalDegree":0,"birthPlace":"Herentals","birthCountry":"Belgium","deathPlace":"Schaerbeek","deathCountry":"Belgium","nativeName":"Charles-Auguste Fraikin","nativeLang":"fr","image":"http://commons.wikimedia.org/wiki/Special:FilePath/Charles%20Auguste%20Fraikin%20%28WMH%20Bd%2008-1860%20S%20554%29.jpg","authorityTypes":["bnf","dnb","ulan","viaf"],"authorityLinks":[{"id":"149741615","type":"bnf","url":"https://catalogue.bnf.fr/ark:/12148/cb149741615"},{"id":"117529087","type":"dnb","url":"https://d-nb.info/gnd/117529087"},{"id":"500121609","type":"ulan","url":"https://www.getty.edu/vow/ULANFullDisplay?find=&role=&nation=&subjectid=500121609"},{"id":"42617686","type":"viaf","url":"https://viaf.org/en/viaf/42617686"}],"sitelinkCount":9,"nonEnSitelinkCount":8,"inclusionSignals":["sitelinks"],"gettyVerified":{"ulanId":"500121609","url":"https://www.getty.edu/vow/ULANFullDisplay?find=&role=&nation=&subjectid=500121609","label":"Fraikin, Charles-Auguste","birthYear":1817,"birthPlace":"Herentals","deathYear":1893,"deathPlace":"Schaerbeek","nationalities":["Belgian"],"agreement":{"birthYear":"match","deathYear":"match","birthPlace":true,"deathPlace":true,"natJaccard":1}}}