{"qid":"Q714577","name":"Alajos Strobl","birthYear":1856,"deathYear":1926,"alive":false,"gender":"male","movement":"No movement listed","citizenship":"Hungary","citizenships":["Hungary"],"birthDecade":1850,"inDegree":1,"outDegree":1,"totalDegree":2,"birthPlace":"Liptovsk\u00fd Hr\u00e1dok","birthCountry":"Slovakia","deathPlace":"Budapest","deathCountry":"Hungary","nativeName":"Strobl Alajos","nativeLang":"hu","image":"http://commons.wikimedia.org/wiki/Special:FilePath/Temple%20Alajos%20Str%C3%B3bl%20at%20Work%201880s.jpg","authorityTypes":["dnb","lcnaf","viaf"],"authorityLinks":[{"id":"132694972","type":"dnb","url":"https://d-nb.info/gnd/132694972"},{"id":"n84210354","type":"lcnaf","url":"https://id.loc.gov/authorities/names/n84210354"},{"id":"11014418","type":"viaf","url":"https://viaf.org/en/viaf/11014418"}],"sitelinkCount":10,"nonEnSitelinkCount":9,"inclusionSignals":["edge","sitelinks"]}