{"qid":"Q720832","name":"Chris Burden","birthYear":1946,"deathYear":2015,"alive":false,"gender":"male","movement":"conceptual art","citizenship":"United States","citizenships":["United States"],"birthDecade":1940,"inDegree":0,"outDegree":0,"totalDegree":0,"birthPlace":"Boston","birthCountry":"United States","deathPlace":"Topanga","deathCountry":"United States","nativeName":null,"nativeLang":null,"image":null,"authorityTypes":["bnf","dnb","lcnaf","ulan","viaf"],"authorityLinks":[{"id":"131955784","type":"bnf","url":"https://catalogue.bnf.fr/ark:/12148/cb131955784"},{"id":"118914987","type":"dnb","url":"https://d-nb.info/gnd/118914987"},{"id":"n84104509","type":"lcnaf","url":"https://id.loc.gov/authorities/names/n84104509"},{"id":"500118760","type":"ulan","url":"https://www.getty.edu/vow/ULANFullDisplay?find=&role=&nation=&subjectid=500118760"},{"id":"57413304","type":"viaf","url":"https://viaf.org/en/viaf/57413304"}],"sitelinkCount":15,"nonEnSitelinkCount":14,"inclusionSignals":["movement","sitelinks"]}