{"qid":"Q761255","name":"August Fischer","birthYear":1805,"deathYear":1866,"alive":false,"gender":"male","movement":"No movement listed","citizenship":"Unknown","citizenships":[],"birthDecade":1800,"inDegree":0,"outDegree":1,"totalDegree":1,"birthPlace":"Berlin","birthCountry":"Germany","deathPlace":"Berlin","deathCountry":"Germany","nativeName":null,"nativeLang":null,"image":null,"authorityTypes":["dnb","viaf"],"authorityLinks":[{"id":"117508500","type":"dnb","url":"https://d-nb.info/gnd/117508500"},{"id":"64786037","type":"viaf","url":"https://viaf.org/en/viaf/64786037"}],"sitelinkCount":2,"nonEnSitelinkCount":2,"inclusionSignals":["edge"]}